Workbook
Name Anos: Resumo!$E$16
Name Dividendos_Mensais: Resumo!$E$19
Name Investimento_mensal: Resumo!$E$15
Name Patrimonio_Acumulado: Resumo!$E$18
Name Perfil_Investidor: Resumo!$E$29
Name rendimento_carteira: Resumo!$E$11
Name Salario: Resumo!$E$10
Name Sugestao_investimento: Resumo!$E$12
Name Taxa_rendimento_mensal: Resumo!$E$17

Sheet Resumo
B2: \($‿$)/ - Invest Fácil! Calculadora de FII
B9: INFORMAÇÕES DO INVESTIDOR
B10: Salário | E10: 5000
B11: Rendimento Carteira | E11: 0.01
B12: Sugestão de Investimento | E12: =E10*20% -> 1000
B14: INVESTIMENTO MENSAL
B15: Quanto investir por mês? | E15: 500
B16: Por quantos anos? | E16: 5
B17: Taxa de Rendimento mensal? | E17: 0.01
B18: Patrimônio acumulado? | E18: =FV(Taxa_rendimento_mensal,Anos*12,Investimento_mensal*-1) -> 40834.835
B19: Dividendos mensais? | E19: =Patrimonio_Acumulado*rendimento_carteira -> 408.34835
B21: Cenários | D21: Valor Futuro | E21: Dividendo
B22: Quanto em 2 Anos? | D22: =FV(Taxa_rendimento_mensal,VLOOKUP(B22,'Referencias de busca'!$B$24:$D$29,3,FALSE),Investimento_mensal*-1) -> 13486.732 | E22: =D22*rendimento_carteira -> 134.86732
B23: Quanto em 5 Anos? | D23: =FV(Taxa_rendimento_mensal,VLOOKUP(B23,'Referencias de busca'!$B$24:$D$29,3,FALSE),Investimento_mensal*-1) -> 40834.835 | E23: =D23*rendimento_carteira -> 408.34835
B24: Quanto em 10 Anos? | D24: =FV(Taxa_rendimento_mensal,VLOOKUP(B24,'Referencias de busca'!$B$24:$D$29,3,FALSE),Investimento_mensal*-1) -> 115019.34 | E24: =D24*rendimento_carteira -> 1150.1934
B25: Quanto em 20 Anos? | D25: =FV(Taxa_rendimento_mensal,VLOOKUP(B25,'Referencias de busca'!$B$24:$D$29,3,FALSE),Investimento_mensal*-1) -> 494627.68 | E25: =D25*rendimento_carteira -> 4946.2768
B26: Quanto em 30 Anos? | D26: =FV(Taxa_rendimento_mensal,VLOOKUP(B26,'Referencias de busca'!$B$24:$D$29,3,FALSE),Investimento_mensal*-1) -> 1747482.1 | E26: =D26*rendimento_carteira -> 17474.821
B29: Perfil de investidor | E29: Conservador
B30: Valor investido por mês | E30: =Investimento_mensal -> 500
B32: Categoria de FII | D32: Percentual Sugerido | E32: Valores
B33: Desenvolvimento | D33: =VLOOKUP(_xlfn.CONCAT(Perfil_Investidor,"-",B33),'Referencias de busca'!$B$4:$E$21,4,FALSE) -> 0 | E33: =D33*$E$30 -> 0
B34: FOFs | D34: =VLOOKUP(_xlfn.CONCAT(Perfil_Investidor,"-",B34),'Referencias de busca'!$B$4:$E$21,4,FALSE) -> 0.1 | E34: =D34*$E$30 -> 50
B35: Híbrido | D35: =VLOOKUP(_xlfn.CONCAT(Perfil_Investidor,"-",B35),'Referencias de busca'!$B$4:$E$21,4,FALSE) -> 0.1 | E35: =D35*$E$30 -> 50
B36: Hotelaria | D36: =VLOOKUP(_xlfn.CONCAT(Perfil_Investidor,"-",B36),'Referencias de busca'!$B$4:$E$21,4,FALSE) -> 0 | E36: =D36*$E$30 -> 0
B37: Papel | D37: =VLOOKUP(_xlfn.CONCAT(Perfil_Investidor,"-",B37),'Referencias de busca'!$B$4:$E$21,4,FALSE) -> 0.3 | E37: =D37*$E$30 -> 150
B38: Tijolo | D38: =VLOOKUP(_xlfn.CONCAT(Perfil_Investidor,"-",B38),'Referencias de busca'!$B$4:$E$21,4,FALSE) -> 0.5 | E38: =D38*$E$30 -> 250
B39: TOTAL | D39: =SUM(D33:D38) -> 1 | E39: =SUM(E33:E38) -> 500

Sheet Referencias de busca
B2: Referência de Percentual de FII
B3: Chave | C3: Perfil | D3: Tipo de FII | E3: Percentual
B4: Conservador-DESENVOLVIMENTO | C4: Conservador | D4: Desenvolvimento | E4: 0
B5: Conservador-FOFs | C5: Conservador | D5: FOFs | E5: 0.1
B6: Conservador-HÍBRIDO | C6: Conservador | D6: Híbrido | E6: 0.1
B7: Conservador-HOTELARIA | C7: Conservador | D7: Hotelaria | E7: 0
B8: Conservador-PAPEL | C8: Conservador | D8: Papel | E8: 0.3
B9: Conservador-TIJOLO | C9: Conservador | D9: Tijolo | E9: 0.5
B10: Moderado-DESENVOLVIMENTO | C10: Moderado | D10: Desenvolvimento | E10: 0
B11: Moderado-FOFs | C11: Moderado | D11: FOFs | E11: 0.1
B12: Moderado-HÍBRIDO | C12: Moderado | D12: Híbrido | E12: 0.1
B13: Moderado-HOTELARIA | C13: Moderado | D13: Hotelaria | E13: 0.05
B14: Moderado-PAPEL | C14: Moderado | D14: Papel | E14: 0.35
B15: Moderado-TIJOLO | C15: Moderado | D15: Tijolo | E15: 0.4
... B21: Agressivo-TIJOLO | C21: Agressivo | D21: Tijolo | E21: 0.1
B23: Referência de Anos
B24: Chave | C24: Ano | D24: Mês
B25: Quanto em 2 Anos? | C25: 2 | D25: =C25*12 -> 24
B26: Quanto em 5 Anos? | C26: 5 | D26: =C26*12 -> 60
B27: Quanto em 10 Anos? | C27: 10 | D27: =C27*12 -> 120
B28: Quanto em 20 Anos? | C28: 20 | D28: =C28*12 -> 240
B29: Quanto em 30 Anos? | C29: 30 | D29: =C29*12 -> 360
